{
  "screen_id": "0060",
  "screen_name": "한도부여결과조회(개사자전용)",
  "channel": "mobile web (개인사업자)",
  "targets": "개인사업자",
  "action": "정보조회",
  "processing_core_call": true,
  "processing_domain": "심사",
  "processing_purpose": "부여한도확인",
  "purpose": "심사에서 산출된 업체 총한도(심사부여한도)를 고객에게 안내",
  "fields": [
    {
      "key": "심사부여한도",
      "required": false,
      "type": "readonly(number)",
      "unit": "만원",
      "note": "조회 결과 표시"
    }
  ],
  "control_rules": [
    "조회 실패/타임아웃 시 재시도 버튼 또는 고객 안내 토스트",
    "단위 표기(만원) 고정, 숫자 포맷팅(천단위 콤마) 옵션",
    "다음 단계로의 이동은 조회성 화면이라도 허용(정책에 따라 블로킹 가능)"
  ],
  "backend": {
    "domain": "심사(처리계)",
    "txn": "한도부여결과 조회",
    "notes": "사업자번호/신청세션 키로 조회. 오류코드별 리트라이/안내 정책 정의 필요"
  },
  "audit_log_points": [
    "조회 성공/실패 여부 및 응답코드",
    "표시된 심사부여한도 값(로그는 마스킹 또는 범주화 고려)",
    "다음 버튼 클릭 시점"
  ],
  "notes": [
    "주어진 스크린샷 톤앤매너(상단 단계, 안내 문구, 읽기전용 필드, 유의사항) 반영",
    "문구/용어는 법무/심사와 확정 후 반영",
    "후속 화면은 0061(신분증 정보) 또는 0062(필수확인사항, 개인전용)로 정책에 맞게 연결"
  ]
}